cli/__init__.py
cli/main.py
cli/container/__init__.py
cli/container/build.py
cli/container/image.py
cli/container/pull.py
cli/container/run.py
cli/util/__init__.py
cli/util/console.py
saloon-0.1.2.dist-info/LICENSE
saloon-0.1.2.dist-info/METADATA
saloon-0.1.2.dist-info/WHEEL
saloon-0.1.2.dist-info/entry_points.txt
saloon-0.1.2.dist-info/top_level.txt
saloon-0.1.2.dist-info/RECORD
