Metadata-Version: 2.1
Name: saloon
Version: 0.1.2
Summary: A pentester's Docker container that does some really nasty things
Home-page: https://github.com/hexcowboy/saloon
Author: hexcowboy <hex@cowboy.dev
License: MIT
Platform: UNKNOWN
Requires-Dist: click (==8.0.1)
Requires-Dist: docker (==5.0.0)
Requires-Dist: dockerpty (==0.4.1)
Requires-Dist: nox (==2021.6.12)
Requires-Dist: Pygments (==2.9.0)
Requires-Dist: rich (==10.3.0)
Requires-Dist: six (==1.16.0)
